setup.py
docs/HISTORY.txt
wow/__init__.py
wow.realmstatusapi.egg-info/PKG-INFO
wow.realmstatusapi.egg-info/SOURCES.txt
wow.realmstatusapi.egg-info/dependency_links.txt
wow.realmstatusapi.egg-info/entry_points.txt
wow.realmstatusapi.egg-info/namespace_packages.txt
wow.realmstatusapi.egg-info/not-zip-safe
wow.realmstatusapi.egg-info/requires.txt
wow.realmstatusapi.egg-info/top_level.txt
wow/realmstatusapi/README.txt
wow/realmstatusapi/__init__.py
wow/realmstatusapi/realmstatus_api.py
wow/realmstatusapi/test_realmstatus.py