Metadata-Version: 1.0
Name: wow.realmstatusapi
Version: 0.3
Summary: Python World of Warcraft Realmstatus API
Home-page: http://code.google.com/p/wowrealmstatusapi/
Author: Marc Goetz
Author-email: goetz.marc@googlemail.com
License: GPL
Keywords: realm status wow warcraft api
Platform: UNKNOWN
Classifier: Programming Language :: Python
